container_tester/__init__.py
container_tester/_cli.py
container_tester/_utils.py
container_tester/app.py
container_tester/docker_backend.py
container_tester-1.0.0rc1.dist-info/licenses/LICENSE
container_tester-1.0.0rc1.dist-info/METADATA
container_tester-1.0.0rc1.dist-info/WHEEL
container_tester-1.0.0rc1.dist-info/entry_points.txt
container_tester-1.0.0rc1.dist-info/top_level.txt
container_tester-1.0.0rc1.dist-info/RECORD
