Metadata-Version: 2.4
Name: container-tester
Version: 1.0.0rc1
Summary: Generate multiple docker cointainers to test projects
Author-email: David Angarita <davidangarita.sistemas@gmail.com>
Maintainer-email: Andrew Pikul <ajpikul@gmail.com>
License: MIT License
Requires-Python: >=3.11
License-File: LICENSE
Requires-Dist: docker>=7.1.0
Requires-Dist: platformdirs>=4.5.0
Requires-Dist: typer>=0.19.2
Dynamic: license-file
